ufr/__init__.py
ufr/main.py
unnfr-0.2.5.dist-info/METADATA
unnfr-0.2.5.dist-info/WHEEL
unnfr-0.2.5.dist-info/entry_points.txt
unnfr-0.2.5.dist-info/top_level.txt
unnfr-0.2.5.dist-info/RECORD
