Metadata-Version: 2.1
Name: unnfr
Version: 0.2.5
Summary: A simple RSS Reader
Home-page: https://github.com/juanvel4000/ufr
Author: juanvel400
Author-email: juanvel400@proton.me
License: MIT
Keywords: rss feed reader
Classifier: Intended Audience :: End Users/Desktop
Classifier: License :: OSI Approved :: MIT License
Classifier: Programming Language :: Python :: 3
Requires-Dist: xmltodict
Requires-Dist: requests
Requires-Dist: inscriptis
